holcrawl
scripts
