Metadata-Version: 1.1
Name: holcrawl
Version: 1.0.1
Summary: A crawler for building Hollywood movies datsets.
Home-page: https://github.com/shaypal5/holcrawl
Author: Shay Palachy
Author-email: shaypal5@gmail.com
License: MIT
Platform: UNKNOWN
Classifier: Development Status :: 4 - Beta
Classifier: Programming Language :: Python
